Workbook

Sheet Peer_Table
A1: Company | B1: Ticker | C1: Selected (1/0) | D1: Selection rationale | E1: Currency | F1: Share Price (CCY) | G1: Market Cap (CCY m) | H1: Enterprise Value (CCY m) | I1: Net Debt (CCY m) | J1: Equity Beta | K1: FX to EUR | L1: Share Price (EUR) | M1: Market Cap (EUR m) | N1: Enterprise Value (EUR m) | O1: Net Debt (EUR m) | P1: Revenue (CCY m) | R1: EBITDA (CCY m) | T1: EBIT (CCY m) | V1: EV/Sales | X1: EV/EBITDA | Z1: EV/EBIT | AB1: Net Debt/EBITDA | AC1: EBITDA Margin
P2: 2023 | Q2: 2024 | R2: 2023 | S2: 2024 | T2: 2023 | U2: 2024 | V2: 2023 | W2: 2024 | X2: 2023 | Y2: 2024 | Z2: 2023 | AA2: 2024 | AC2: 2023 | AD2: 2024
A3: Aalberts | B3: AALB.AS | C3: 1 | D3: Closest diversified industrial technology peer | E3: EUR | F3: 34.48 | G3: 3738.6586 | H3: 4813.8557 | I3: 596.8 | J3: 1.264 | K3: 1 | L3: 34.48 | M3: 3738.6586 | N3: 4813.8557 | O3: 596.8 | P3: 3324 | Q3: 3148.6 | R3: 658.8 | S3: 511.1 | T3: 459.6 | U3: 292.6 | V3: =IF(OR(P3="",P3=0),"",H3/P3) | W3: =IF(OR(Q3="",Q3=0),"",H3/Q3) | X3: =IF(OR(R3="",R3=0),"",H3/R3) | Y3: =IF(OR(S3="",S3=0),"",H3/S3) | Z3: =IF(OR(T3="",T3=0),"",H3/T3) | AA3: =IF(OR(U3="",U3=0),"",H3/U3) | AB3: =IF(OR(S3="",S3=0),"",I3/S3) | AC3: =IF(OR(P3="",P3=0),"",R3/P3) | AD3: =IF(OR(Q3="",Q3=0),"",S3/Q3)
A4: Dürr AG | B4: DUE.DE | C4: 1 | D4: Industrial automation/manufacturing systems exposure comparable to TKH | E4: EUR | F4: 23.15 | G4: 1602.0282 | H4: 2059.1201 | I4: 493.626 | J4: 1.33 | K4: 1 | L4: 23.15 | M4: 1602.0282 | N4: 2059.1201 | O4: 493.626 | P4: 4196.029 | Q4: 4290.936 | R4: 303.593 | S4: 345.838 | T4: 172.792 | U4: 183.517 | V4: =IF(OR(P4="",P4=0),"",H4/P4) | W4: =IF(OR(Q4="",Q4=0),"",H4/Q4) | X4: =IF(OR(R4="",R4=0),"",H4/R4) | Y4: =IF(OR(S4="",S4=0),"",H4/S4) | Z4: =IF(OR(T4="",T4=0),"",H4/T4) | AA4: =IF(OR(U4="",U4=0),"",H4/U4) | AB4: =IF(OR(S4="",S4=0),"",I4/S4) | AC4: =IF(OR(P4="",P4=0),"",R4/P4) | AD4: =IF(OR(Q4="",Q4=0),"",S4/Q4)
A5: Basler | B5: BSL.DE | C5: 1 | D5: Direct machine vision hardware/software comparable | E5: EUR | F5: 15.66 | G5: 481.5079 | H5: 522.99792 | I5: 50.76 | J5: 2.419 | K5: 1 | L5: 15.66 | M5: 481.5079 | N5: 522.99792 | O5: 50.76 | P5: 201.813 | Q5: 184.926 | R5: 5.223 | S5: 9.438 | T5: -18.377 | U5: -10.357 | V5: =IF(OR(P5="",P5=0),"",H5/P5) | W5: =IF(OR(Q5="",Q5=0),"",H5/Q5) | X5: =IF(OR(R5="",R5=0),"",H5/R5) | Y5: =IF(OR(S5="",S5=0),"",H5/S5) | Z5: =IF(OR(T5="",T5=0),"",H5/T5) | AA5: =IF(OR(U5="",U5=0),"",H5/U5) | AB5: =IF(OR(S5="",S5=0),"",I5/S5) | AC5: =IF(OR(P5="",P5=0),"",R5/P5) | AD5: =IF(OR(Q5="",Q5=0),"",S5/Q5)
A6: Cognex | B6: COGX | C6: 1 | D6: Global machine vision leader benchmark | E6: USD | F6: 42.369999 | G6: 7101.1292 | H6: 6879.7885 | I6: -115.877 | J6: 1.534 | K6: 0.84904999 | L6: 35.974247 | M6: 6029.2137 | N6: 5841.2844 | O6: -98.385365 | P6: 837.547 | Q6: 914.515 | R6: 144.582 | S6: 147.754 | T6: 122.702 | U6: 115.065 | V6: =IF(OR(P6="",P6=0),"",H6/P6) | W6: =IF(OR(Q6="",Q6=0),"",H6/Q6) | X6: =IF(OR(R6="",R6=0),"",H6/R6) | Y6: =IF(OR(S6="",S6=0),"",H6/S6) | Z6: =IF(OR(T6="",T6=0),"",H6/T6) | AA6: =IF(OR(U6="",U6=0),"",H6/U6) | AB6: =IF(OR(S6="",S6=0),"",I6/S6) | AC6: =IF(OR(P6="",P6=0),"",R6/P6) | AD6: =IF(OR(Q6="",Q6=0),"",S6/Q6)
A7: Jenoptik | B7: JEN.DE | C7: 1 | D7: Photonics and optical systems overlap | E7: EUR | F7: 26.219999 | G7: 1500.7834 | H7: 1874.8805 | I7: 396.219 | J7: 1.25 | K7: 1 | L7: 26.219999 | M7: 1500.7834 | N7: 1874.8805 | O7: 396.219 | P7: 1066.048 | Q7: 1115.787 | R7: 198.693 | S7: 220.838 | T7: 127.823 | U7: 145.926 | V7: =IF(OR(P7="",P7=0),"",H7/P7) | W7: =IF(OR(Q7="",Q7=0),"",H7/Q7) | X7: =IF(OR(R7="",R7=0),"",H7/R7) | Y7: =IF(OR(S7="",S7=0),"",H7/S7) | Z7: =IF(OR(T7="",T7=0),"",H7/T7) | AA7: =IF(OR(U7="",U7=0),"",H7/U7) | AB7: =IF(OR(S7="",S7=0),"",I7/S7) | AC7: =IF(OR(P7="",P7=0),"",R7/P7) | AD7: =IF(OR(Q7="",Q7=0),"",S7/Q7)
A8: Huber+Suhner | B8: HUBN.SW | C8: 1 | D8: Connectivity and industrial cabling exposure | E8: CHF | F8: 173.39999 | G8: 3199.8126 | H8: 3019.9644 | I8: -174.133 | J8: 0.725 | K8: 1.091584 | L8: 189.28065 | M8: 3492.8641 | N8: 3296.5447 | O8: -190.08079 | P8: 851.062 | Q8: 893.874 | R8: 107.607 | S8: 121.844 | T8: 74.667 | U8: 85.859 | V8: =IF(OR(P8="",P8=0),"",H8/P8) | W8: =IF(OR(Q8="",Q8=0),"",H8/Q8) | X8: =IF(OR(R8="",R8=0),"",H8/R8) | Y8: =IF(OR(S8="",S8=0),"",H8/S8) | Z8: =IF(OR(T8="",T8=0),"",H8/T8) | AA8: =IF(OR(U8="",U8=0),"",H8/U8) | AB8: =IF(OR(S8="",S8=0),"",I8/S8) | AC8: =IF(OR(P8="",P8=0),"",R8/P8) | AD8: =IF(OR(Q8="",Q8=0),"",S8/Q8)
A9: NKT | B9: NKT.CO | C9: 1 | D9: Power/subsea cable and electrification exposure | E9: DKK | F9: 824.5 | G9: 44069.896 | H9: 43652.141 | I9: -1280 | J9: 0.68 | K9: 0.13390601 | L9: 110.4055 | M9: 5901.2238 | N9: 5845.2839 | O9: -171.39969 | P9: 2567 | Q9: 3252 | R9: 249 | S9: 384 | T9: 159 | U9: 282 | V9: =IF(OR(P9="",P9=0),"",H9/P9) | W9: =IF(OR(Q9="",Q9=0),"",H9/Q9) | X9: =IF(OR(R9="",R9=0),"",H9/R9) | Y9: =IF(OR(S9="",S9=0),"",H9/S9) | Z9: =IF(OR(T9="",T9=0),"",H9/T9) | AA9: =IF(OR(U9="",U9=0),"",H9/U9) | AB9: =IF(OR(S9="",S9=0),"",I9/S9) | AC9: =IF(OR(P9="",P9=0),"",R9/P9) | AD9: =IF(OR(Q9="",Q9=0),"",S9/Q9)
A10: Mersen | B10: MRN.PA | C10: 1 | D10: Electrical components and power management peer | E10: EUR | F10: 25.9 | G10: 630.5639 | H10: 1107.7879 | I10: 426.2 | J10: 1.331 | K10: 1 | L10: 25.9 | M10: 630.5639 | N10: 1107.7879 | O10: 426.2 | P10: 1210.9 | Q10: 1243.6 | R10: 191.4 | S10: 176.5 | T10: 126 | U10: 102 | V10: =IF(OR(P10="",P10=0),"",H10/P10) | W10: =IF(OR(Q10="",Q10=0),"",H10/Q10) | X10: =IF(OR(R10="",R10=0),"",H10/R10) | Y10: =IF(OR(S10="",S10=0),"",H10/S10) | Z10: =IF(OR(T10="",T10=0),"",H10/T10) | AA10: =IF(OR(U10="",U10=0),"",H10/U10) | AB10: =IF(OR(S10="",S10=0),"",I10/S10) | AC10: =IF(OR(P10="",P10=0),"",R10/P10) | AD10: =IF(OR(Q10="",Q10=0),"",S10/Q10)
A11: Arcadis | B11: ARCAD.AS | C11: 0 | D11: Services-heavy model, less product/asset intensity | E11: EUR | F11: 38.52 | G11: 3292.7593 | H11: 4499.3014 | I11: 759 | J11: 0.658 | K11: 1 | L11: 38.52 | M11: 3292.7593 | N11: 4499.3014 | O11: 759 | P11: 5003 | Q11: 4995 | R11: 464 | S11: 545 | T11: 290 | U11: 405 | V11: =IF(OR(P11="",P11=0),"",H11/P11) | W11: =IF(OR(Q11="",Q11=0),"",H11/Q11) | X11: =IF(OR(R11="",R11=0),"",H11/R11) | Y11: =IF(OR(S11="",S11=0),"",H11/S11) | Z11: =IF(OR(T11="",T11=0),"",H11/T11) | AA11: =IF(OR(U11="",U11=0),"",H11/U11) | AB11: =IF(OR(S11="",S11=0),"",I11/S11) | AC11: =IF(OR(P11="",P11=0),"",R11/P11) | AD11: =IF(OR(Q11="",Q11=0),"",S11/Q11)
A12: Fugro | B12: FUR.AS | C12: 0 | D12: Geo-data/offshore services, weaker industrial comparability | E12: EUR | F12: 11.28 | G12: 1246.3387 | H12: 1699.1387 | I12: 96.159 | J12: 0.796 | K12: 1 | L12: 11.28 | M12: 1246.3387 | N12: 1699.1387 | O12: 96.159 | P12: 2187.361 | Q12: 2275.434 | R12: 397.619 | S12: 513.103 | T12: 252.443 | U12: 344.074 | V12: =IF(OR(P12="",P12=0),"",H12/P12) | W12: =IF(OR(Q12="",Q12=0),"",H12/Q12) | X12: =IF(OR(R12="",R12=0),"",H12/R12) | Y12: =IF(OR(S12="",S12=0),"",H12/S12) | Z12: =IF(OR(T12="",T12=0),"",H12/T12) | AA12: =IF(OR(U12="",U12=0),"",H12/U12) | AB12: =IF(OR(S12="",S12=0),"",I12/S12) | AC12: =IF(OR(P12="",P12=0),"",R12/P12) | AD12: =IF(OR(Q12="",Q12=0),"",S12/Q12)
A13: SBM Offshore | B13: SBMO.AS | C13: 0 | D13: Project/offshore leasing model not close to TKH | E13: EUR | F13: 29.4 | G13: 4941.0775 | H13: 15331.299 | I13: 8137 | J13: 0.791 | K13: 1 | L13: 29.4 | M13: 4941.0775 | N13: 15331.299 | O13: 8137 | P13: 4962 | Q13: 4784 | R13: 1391 | S13: 1200 | T13: 1326 | U13: 1130 | V13: =IF(OR(P13="",P13=0),"",H13/P13) | W13: =IF(OR(Q13="",Q13=0),"",H13/Q13) | X13: =IF(OR(R13="",R13=0),"",H13/R13) | Y13: =IF(OR(S13="",S13=0),"",H13/S13) | Z13: =IF(OR(T13="",T13=0),"",H13/T13) | AA13: =IF(OR(U13="",U13=0),"",H13/U13) | AB13: =IF(OR(S13="",S13=0),"",I13/S13) | AC13: =IF(OR(P13="",P13=0),"",R13/P13) | AD13: =IF(OR(Q13="",Q13=0),"",S13/Q13)
A14: Vopak | B14: VPK.AS | C14: 0 | D14: Tank storage infrastructure, limited operating overlap | E14: EUR | F14: 42.959999 | G14: 4921.4592 | H14: 7800.0015 | I14: 2672 | J14: 0.86 | K14: 1 | L14: 42.959999 | M14: 4921.4592 | N14: 7800.0015 | O14: 2672 | P14: 1425.6 | Q14: 1315.6 | R14: 1016.8 | S14: 925.2 | T14: 693.8 | U14: 617.8 | V14: =IF(OR(P14="",P14=0),"",H14/P14) | W14: =IF(OR(Q14="",Q14=0),"",H14/Q14) | X14: =IF(OR(R14="",R14=0),"",H14/R14) | Y14: =IF(OR(S14="",S14=0),"",H14/S14) | Z14: =IF(OR(T14="",T14=0),"",H14/T14) | AA14: =IF(OR(U14="",U14=0),"",H14/U14) | AB14: =IF(OR(S14="",S14=0),"",I14/S14) | AC14: =IF(OR(P14="",P14=0),"",R14/P14) | AD14: =IF(OR(Q14="",Q14=0),"",S14/Q14)
A15: TKH (subject company) | B15: TWEKA.AS | C15: 0 | D15: Subject company reference (excluded from peer stats) | E15: EUR | F15: 39.32 | G15: 1568.2474 | H15: 2252.5312 | I15: 584.726 | J15: 0.99 | K15: 1 | L15: 39.32 | M15: 1568.2474 | N15: 2252.5312 | O15: 584.726 | P15: 1847.532 | Q15: 1712.735 | R15: 331.628 | S15: 266.821 | T15: 225.855 | U15: 153.673 | V15: =IF(OR(P15="",P15=0),"",H15/P15) | W15: =IF(OR(Q15="",Q15=0),"",H15/Q15) | X15: =IF(OR(R15="",R15=0),"",H15/R15) | Y15: =IF(OR(S15="",S15=0),"",H15/S15) | Z15: =IF(OR(T15="",T15=0),"",H15/T15) | AA15: =IF(OR(U15="",U15=0),"",H15/U15) | AB15: =IF(OR(S15="",S15=0),"",I15/S15) | AC15: =IF(OR(P15="",P15=0),"",R15/P15) | AD15: =IF(OR(Q15="",Q15=0),"",S15/Q15)
A17: Selected peers average | V17: =IFERROR(AVERAGEIF(C3:C15,1,V3:V15),"") | W17: =IFERROR(AVERAGEIF(C3:C15,1,W3:W15),"") | X17: =IFERROR(AVERAGEIF(C3:C15,1,X3:X15),"") | Y17: =IFERROR(AVERAGEIF(C3:C15,1,Y3:Y15),"") | Z17: =IFERROR(AVERAGEIF(C3:C15,1,Z3:Z15),"") | AA17: =IFERROR(AVERAGEIF(C3:C15,1,AA3:AA15),"")
A18: Selected peers median | V18: =IFERROR(MEDIAN(FILTER(V3:V15,(C3:C15=1)*(V3:V15<>""))),"") | W18: =IFERROR(MEDIAN(FILTER(W3:W15,(C3:C15=1)*(W3:W15<>""))),"") | X18: =IFERROR(MEDIAN(FILTER(X3:X15,(C3:C15=1)*(X3:X15<>""))),"") | Y18: =IFERROR(MEDIAN(FILTER(Y3:Y15,(C3:C15=1)*(Y3:Y15<>""))),"") | Z18: =IFERROR(MEDIAN(FILTER(Z3:Z15,(C3:C15=1)*(Z3:Z15<>""))),"") | AA18: =IFERROR(MEDIAN(FILTER(AA3:AA15,(C3:C15=1)*(AA3:AA15<>""))),"")
A21: TKH Inputs
A22: Metric | B22: 2023 | C22: 2024
A23: Revenue (CCY m) | B23: =IFERROR(INDEX(P3:P15,MATCH("TWEKA.AS",B3:B15,0)),"") | C23: =IFERROR(INDEX(Q3:Q15,MATCH("TWEKA.AS",B3:B15,0)),"")
A24: EBITDA (CCY m) | B24: =IFERROR(INDEX(R3:R15,MATCH("TWEKA.AS",B3:B15,0)),"") | C24: =IFERROR(INDEX(S3:S15,MATCH("TWEKA.AS",B3:B15,0)),"")
A25: EBIT (CCY m) | B25: =IFERROR(INDEX(T3:T15,MATCH("TWEKA.AS",B3:B15,0)),"") | C25: =IFERROR(INDEX(U3:U15,MATCH("TWEKA.AS",B3:B15,0)),"")
A26: Net Debt (CCY m) | C26: =IFERROR(INDEX(I3:I15,MATCH("TWEKA.AS",B3:B15,0)),"")
A27: Adjustments (CCY m) | C27: 0
A28: Shares Outstanding (m)
A31: TKH valuation (Selected peers)
A32: Multiple | B32: Year | C32: Selected Avg | D32: Selected Median | E32: TKH Metric (CCY m) | F32: Implied EV (Avg) | G32: Implied EV (Median) | H32: Net Debt (CCY m) | I32: Adjustments (CCY m) | J32: Equity Value (Avg) | K32: Equity Value (Median) | L32: Shares (m) | M32: Per Share (Avg) | N32: Per Share (Median)
A33: EV/Sales | B33: 2023 | C33: =V17 | D33: =V18 | E33: =B23 | F33: =IF(OR(C33="",E33=""),"",C33*E33) | G33: =IF(OR(D33="",E33=""),"",D33*E33) | H33: =C26 | I33: =C27 | J33: =IF(F33="","",F33-H33+I33) | K33: =IF(G33="","",G33-H33+I33) | L33: =C28 | M33: =IF(OR(J33="",L33=""),"",J33/L33) | N33: =IF(OR(K33="",L33=""),"",K33/L33)
A34: EV/Sales | B34: 2024 | C34: =W17 | D34: =W18 | E34: =C23 | F34: =IF(OR(C34="",E34=""),"",C34*E34) | G34: =IF(OR(D34="",E34=""),"",D34*E34) | H34: =C26 | I34: =C27 | J34: =IF(F34="","",F34-H34+I34) | K34: =IF(G34="","",G34-H34+I34) | L34: =C28 | M34: =IF(OR(J34="",L34=""),"",J34/L34) | N34: =IF(OR(K34="",L34=""),"",K34/L34)
A35: EV/EBITDA | B35: 2023 | C35: =X17 | D35: =X18 | E35: =B24 | F35: =IF(OR(C35="",E35=""),"",C35*E35) | G35: =IF(OR(D35="",E35=""),"",D35*E35) | H35: =C26 | I35: =C27 | J35: =IF(F35="","",F35-H35+I35) | K35: =IF(G35="","",G35-H35+I35) | L35: =C28 | M35: =IF(OR(J35="",L35=""),"",J35/L35) | N35: =IF(OR(K35="",L35=""),"",K35/L35)
A36: EV/EBITDA | B36: 2024 | C36: =Y17 | D36: =Y18 | E36: =C24 | F36: =IF(OR(C36="",E36=""),"",C36*E36) | G36: =IF(OR(D36="",E36=""),"",D36*E36) | H36: =C26 | I36: =C27 | J36: =IF(F36="","",F36-H36+I36) | K36: =IF(G36="","",G36-H36+I36) | L36: =C28 | M36: =IF(OR(J36="",L36=""),"",J36/L36) | N36: =IF(OR(K36="",L36=""),"",K36/L36)
A37: EV/EBIT | B37: 2023 | C37: =Z17 | D37: =Z18 | E37: =B25 | F37: =IF(OR(C37="",E37=""),"",C37*E37) | G37: =IF(OR(D37="",E37=""),"",D37*E37) | H37: =C26 | I37: =C27 | J37: =IF(F37="","",F37-H37+I37) | K37: =IF(G37="","",G37-H37+I37) | L37: =C28 | M37: =IF(OR(J37="",L37=""),"",J37/L37) | N37: =IF(OR(K37="",L37=""),"",K37/L37)
A38: EV/EBIT | B38: 2024 | C38: =AA17 | D38: =AA18 | E38: =C25 | F38: =IF(OR(C38="",E38=""),"",C38*E38) | G38: =IF(OR(D38="",E38=""),"",D38*E38) | H38: =C26 | I38: =C27 | J38: =IF(F38="","",F38-H38+I38) | K38: =IF(G38="","",G38-H38+I38) | L38: =C28 | M38: =IF(OR(J38="",L38=""),"",J38/L38) | N38: =IF(OR(K38="",L38=""),"",K38/L38)

Sheet Instructions
A1: TKH peer workbook | B1: Generated on 2026-02-08
A2: How to populate live KPIs | B2: Run fill_from_yahoo.py or paste current values for market data and operating metrics.
A3: Suggested data sources | B3: Bloomberg, Capital IQ, FactSet, Refinitiv, or Yahoo Finance.
A4: Units | B4: Market Cap/EV/Revenue/EBITDA/EBIT/Net Debt are stored in CCY m; shares in m; EUR columns use FX.
A5: Selection result | B5: Rows with Selected=1 drive the peer summary and valuation block.

Sheet WACC_Model
A1: Company | B1: Ticker | C1: Selected (1/0) | D1: Equity Beta | E1: Net Debt (CCY m) | F1: Market Cap (CCY m) | G1: Debt/Equity | H1: Unlevered Beta
A2: =Peer_Table!A3 | B2: =Peer_Table!B3 | C2: =Peer_Table!C3 | D2: =Peer_Table!J3 | E2: =Peer_Table!I3 | F2: =Peer_Table!G3 | G2: =IF(OR(F2="",F2=0,E2=""),"",E2/F2) | H2: =IF(OR(D2="",G2=""),"",D2/(1+(1-B21)*G2))
A3: =Peer_Table!A4 | B3: =Peer_Table!B4 | C3: =Peer_Table!C4 | D3: =Peer_Table!J4 | E3: =Peer_Table!I4 | F3: =Peer_Table!G4 | G3: =IF(OR(F3="",F3=0,E3=""),"",E3/F3) | H3: =IF(OR(D3="",G3=""),"",D3/(1+(1-B21)*G3))
A4: =Peer_Table!A5 | B4: =Peer_Table!B5 | C4: =Peer_Table!C5 | D4: =Peer_Table!J5 | E4: =Peer_Table!I5 | F4: =Peer_Table!G5 | G4: =IF(OR(F4="",F4=0,E4=""),"",E4/F4) | H4: =IF(OR(D4="",G4=""),"",D4/(1+(1-B21)*G4))
A5: =Peer_Table!A6 | B5: =Peer_Table!B6 | C5: =Peer_Table!C6 | D5: =Peer_Table!J6 | E5: =Peer_Table!I6 | F5: =Peer_Table!G6 | G5: =IF(OR(F5="",F5=0,E5=""),"",E5/F5) | H5: =IF(OR(D5="",G5=""),"",D5/(1+(1-B21)*G5))
A6: =Peer_Table!A7 | B6: =Peer_Table!B7 | C6: =Peer_Table!C7 | D6: =Peer_Table!J7 | E6: =Peer_Table!I7 | F6: =Peer_Table!G7 | G6: =IF(OR(F6="",F6=0,E6=""),"",E6/F6) | H6: =IF(OR(D6="",G6=""),"",D6/(1+(1-B21)*G6))
A7: =Peer_Table!A8 | B7: =Peer_Table!B8 | C7: =Peer_Table!C8 | D7: =Peer_Table!J8 | E7: =Peer_Table!I8 | F7: =Peer_Table!G8 | G7: =IF(OR(F7="",F7=0,E7=""),"",E7/F7) | H7: =IF(OR(D7="",G7=""),"",D7/(1+(1-B21)*G7))
A8: =Peer_Table!A9 | B8: =Peer_Table!B9 | C8: =Peer_Table!C9 | D8: =Peer_Table!J9 | E8: =Peer_Table!I9 | F8: =Peer_Table!G9 | G8: =IF(OR(F8="",F8=0,E8=""),"",E8/F8) | H8: =IF(OR(D8="",G8=""),"",D8/(1+(1-B21)*G8))
A9: =Peer_Table!A10 | B9: =Peer_Table!B10 | C9: =Peer_Table!C10 | D9: =Peer_Table!J10 | E9: =Peer_Table!I10 | F9: =Peer_Table!G10 | G9: =IF(OR(F9="",F9=0,E9=""),"",E9/F9) | H9: =IF(OR(D9="",G9=""),"",D9/(1+(1-B21)*G9))
A10: =Peer_Table!A11 | B10: =Peer_Table!B11 | C10: =Peer_Table!C11 | D10: =Peer_Table!J11 | E10: =Peer_Table!I11 | F10: =Peer_Table!G11 | G10: =IF(OR(F10="",F10=0,E10=""),"",E10/F10) | H10: =IF(OR(D10="",G10=""),"",D10/(1+(1-B21)*G10))
A11: =Peer_Table!A12 | B11: =Peer_Table!B12 | C11: =Peer_Table!C12 | D11: =Peer_Table!J12 | E11: =Peer_Table!I12 | F11: =Peer_Table!G12 | G11: =IF(OR(F11="",F11=0,E11=""),"",E11/F11) | H11: =IF(OR(D11="",G11=""),"",D11/(1+(1-B21)*G11))
A12: =Peer_Table!A13 | B12: =Peer_Table!B13 | C12: =Peer_Table!C13 | D12: =Peer_Table!J13 | E12: =Peer_Table!I13 | F12: =Peer_Table!G13 | G12: =IF(OR(F12="",F12=0,E12=""),"",E12/F12) | H12: =IF(OR(D12="",G12=""),"",D12/(1+(1-B21)*G12))
A13: =Peer_Table!A14 | B13: =Peer_Table!B14 | C13: =Peer_Table!C14 | D13: =Peer_Table!J14 | E13: =Peer_Table!I14 | F13: =Peer_Table!G14 | G13: =IF(OR(F13="",F13=0,E13=""),"",E13/F13) | H13: =IF(OR(D13="",G13=""),"",D13/(1+(1-B21)*G13))
A14: =Peer_Table!A15 | B14: =Peer_Table!B15 | C14: =Peer_Table!C15 | D14: =Peer_Table!J15 | E14: =Peer_Table!I15 | F14: =Peer_Table!G15 | G14: =IF(OR(F14="",F14=0,E14=""),"",E14/F14) | H14: =IF(OR(D14="",G14=""),"",D14/(1+(1-B21)*G14))
A17: WACC Inputs
A18: Risk-free rate | B18: 0.03
A19: Market risk premium | B19: 0.045
A20: Small firm premium | B20: 0.0125
A21: Marginal tax rate | B21: 0.25
A22: Cost of debt (pre-tax) | B22: 0.05
A23: Target debt / equity | B23: 0.25
A25: Selected peers beta summary
A26: Average equity beta | B26: =IFERROR(AVERAGEIF(C2:C14,1,D2:D14),"")
A27: Median equity beta | B27: =IFERROR(MEDIAN(FILTER(D2:D14,(C2:C14=1)*(D2:D14<>""))),"")
A28: Average unlevered beta | B28: =IFERROR(AVERAGEIF(C2:C14,1,H2:H14),"")
A29: Median unlevered beta | B29: =IFERROR(MEDIAN(FILTER(H2:H14,(C2:C14=1)*(H2:H14<>""))),"")
A31: WACC Calculation
A32: Relevered beta | B32: =B28*(1+(1-B21)*B23)
A33: Cost of equity | B33: =B18+B19*B32+B20
A34: Cost of debt (after-tax) | B34: =B22*(1-B21)
A35: Target debt weight | B35: =B23/(1+B23)
A36: Target equity weight | B36: =1-B35
A37: WACC | B37: =B33*B36+B34*B35
